[
  {
    "character_identifier": "NARRATOR",
    "scene_identifier": "SCENE_01",
    "ordinal": 0,
    "text": "The great chamber of the Capulet estate is a whirlwind of activity. Musicians tune their instruments in the gallery while servants scramble to clear the remnants of a feast.",
    "speed": 1.0,
    "audio_description": "narrating",
    "trailing_silence_s": 0.5,
    "start_s": 0.0,
    "end_s": 10.5,
    "duration_s": 10.5
  },
  {
    "character_identifier": "CAPULETS_FIRST_SERVANT",
    "scene_identifier": "SCENE_01",
    "ordinal": 1,
    "text": "Where’s Potpan, that he helps not to take away? He shift a trencher! He scrape a trencher!",
    "speed": 1.0,
    "audio_description": "annoyed, harried",
    "trailing_silence_s": 0.2,
    "start_s": 10.5,
    "end_s": 15.927007,
    "duration_s": 5.427007
  },
  {
    "character_identifier": "CAPULETS_SECOND_SERVANT",
    "scene_identifier": "SCENE_01",
    "ordinal": 2,
    "text": "When good manners shall lie all in one or two men’s hands, and they unwash’d too, ’tis a foul thing.",
    "speed": 1.0,
    "audio_description": "muttering, cynical",
    "trailing_silence_s": 0.2,
    "start_s": 15.927007,
    "end_s": 21.473674,
    "duration_s": 5.546667
  },
  {
    "character_identifier": "CAPULETS_FIRST_SERVANT",
    "scene_identifier": "SCENE_01",
    "ordinal": 3,
    "text": "Away with the join-stools, remove the court-cupboard, look to the plate. Good thou, save me a piece of marchpane; and as thou loves me, let the porter let in Susan Grindstone and Nell. Antony and Potpan!",
    "speed": 1.0,
    "audio_description": "barking orders",
    "trailing_silence_s": 0.2,
    "start_s": 21.473674,
    "end_s": 33.390681,
    "duration_s": 11.917007
  },
  {
    "character_identifier": "CAPULETS_SECOND_SERVANT",
    "scene_identifier": "SCENE_01",
    "ordinal": 4,
    "text": "Ay, boy, ready.",
    "speed": 1.0,
    "audio_description": "shouting back",
    "trailing_silence_s": 0.2,
    "start_s": 33.390681,
    "end_s": 35.337348,
    "duration_s": 1.946667
  },
  {
    "character_identifier": "CAPULETS_FIRST_SERVANT",
    "scene_identifier": "SCENE_01",
    "ordinal": 5,
    "text": "You are looked for and called for, asked for and sought for, in the great chamber.",
    "speed": 1.0,
    "audio_description": "urgent",
    "trailing_silence_s": 0.2,
    "start_s": 35.337348,
    "end_s": 40.784355,
    "duration_s": 5.447007
  },
  {
    "character_identifier": "CAPULETS_SECOND_SERVANT",
    "scene_identifier": "SCENE_01",
    "ordinal": 6,
    "text": "We cannot be here and there too. Cheerly, boys. Be brisk awhile, and the longer liver take all.",
    "speed": 1.0,
    "audio_description": "encouraging",
    "trailing_silence_s": 0.4,
    "start_s": 40.784355,
    "end_s": 47.291022,
    "duration_s": 6.506667
  },
  {
    "character_identifier": "NARRATOR",
    "scene_identifier": "SCENE_01",
    "ordinal": 7,
    "text": "The servants hurry out as Lord Capulet enters, leading a vibrant procession of masked guests and elegant ladies into the hall.",
    "speed": 1.0,
    "audio_description": "narrating",
    "trailing_silence_s": 0.5,
    "start_s": 47.291022,
    "end_s": 55.511022,
    "duration_s": 8.22
  },
  {
    "character_identifier": "CAPULET",
    "scene_identifier": "SCENE_01",
    "ordinal": 8,
    "text": "Welcome, gentlemen, ladies that have their toes unplagu’d with corns will have a bout with you. Ah my mistresses, which of you all will now deny to dance? She that makes dainty, she I’ll swear hath corns. Am I come near ye now?",
    "speed": 1.0,
    "audio_description": "jovial, boisterous",
    "trailing_silence_s": 0.2,
    "start_s": 55.511022,
    "end_s": 68.476033,
    "duration_s": 12.965011
  },
  {
    "character_identifier": "CAPULET",
    "scene_identifier": "SCENE_01",
    "ordinal": 9,
    "text": "Welcome, gentlemen! I have seen the day that I have worn a visor, and could tell a whispering tale in a fair lady’s ear, such as would please; ’tis gone, ’tis gone, ’tis gone, you are welcome, gentlemen! Come, musicians, play.",
    "speed": 1.0,
    "audio_description": "reminiscent, then energetic",
    "trailing_silence_s": 0.3,
    "start_s": 68.476033,
    "end_s": 82.82304,
    "duration_s": 14.347007
  },
  {
    "character_identifier": "CAPULET",
    "scene_identifier": "SCENE_01",
    "ordinal": 10,
    "text": "A hall, a hall, give room! And foot it, girls.",
    "speed": 1.0,
    "audio_description": "commanding, loud",
    "trailing_silence_s": 0.2,
    "start_s": 82.82304,
    "end_s": 86.76970700000001,
    "duration_s": 3.946667
  },
  {
    "character_identifier": "NARRATOR",
    "scene_identifier": "SCENE_01",
    "ordinal": 11,
    "text": "The music swells and the guests begin to dance, their rhythmic footsteps echoing through the room.",
    "speed": 1.0,
    "audio_description": "narrating",
    "trailing_silence_s": 0.8,
    "start_s": 86.76970700000001,
    "end_s": 93.20970700000001,
    "duration_s": 6.44
  },
  {
    "character_identifier": "CAPULET",
    "scene_identifier": "SCENE_01",
    "ordinal": 12,
    "text": "More light, you knaves; and turn the tables up, and quench the fire, the room is grown too hot. Ah sirrah, this unlook’d-for sport comes well. Nay sit, nay sit, good cousin Capulet, for you and I are past our dancing days; how long is’t now since last yourself and I were in a mask?",
    "speed": 1.0,
    "audio_description": "busy, then conversational",
    "trailing_silence_s": 0.2,
    "start_s": 93.20970700000001,
    "end_s": 112.24270000000001,
    "duration_s": 19.032993
  },
  {
    "character_identifier": "CAPULETS_COUSIN",
    "scene_identifier": "SCENE_01",
    "ordinal": 13,
    "text": "By’r Lady, thirty years.",
    "speed": 1.0,
    "audio_description": "raspy, certain",
    "trailing_silence_s": 0.2,
    "start_s": 112.24270000000001,
    "end_s": 114.90936700000002,
    "duration_s": 2.666667
  },
  {
    "character_identifier": "CAPULET",
    "scene_identifier": "SCENE_01",
    "ordinal": 14,
    "text": "What, man, ’tis not so much, ’tis not so much: ’Tis since the nuptial of Lucentio, come Pentecost as quickly as it will, some five and twenty years; and then we mask’d.",
    "speed": 1.0,
    "audio_description": "dismissive, arguing",
    "trailing_silence_s": 0.2,
    "start_s": 114.90936700000002,
    "end_s": 125.85603400000002,
    "duration_s": 10.946667
  },
  {
    "character_identifier": "CAPULETS_COUSIN",
    "scene_identifier": "SCENE_01",
    "ordinal": 15,
    "text": "’Tis more, ’tis more, his son is elder, sir; his son is thirty.",
    "speed": 1.0,
    "audio_description": "insisting",
    "trailing_silence_s": 0.2,
    "start_s": 125.85603400000002,
    "end_s": 130.88270100000003,
    "duration_s": 5.026667
  },
  {
    "character_identifier": "CAPULET",
    "scene_identifier": "SCENE_01",
    "ordinal": 16,
    "text": "Will you tell me that? His son was but a ward two years ago.",
    "speed": 1.0,
    "audio_description": "stubborn",
    "trailing_silence_s": 0.4,
    "start_s": 130.88270100000003,
    "end_s": 134.98970800000004,
    "duration_s": 4.107007
  },
  {
    "character_identifier": "ROMEO",
    "scene_identifier": "SCENE_01",
    "ordinal": 17,
    "text": "What lady is that, which doth enrich the hand of yonder knight?",
    "speed": 1.0,
    "audio_description": "breathless, mesmerized",
    "trailing_silence_s": 0.2,
    "start_s": 134.98970800000004,
    "end_s": 138.34671500000005,
    "duration_s": 3.357007
  },
  {
    "character_identifier": "SERVANT_CAPULET",
    "scene_identifier": "SCENE_01",
    "ordinal": 18,
    "text": "I know not, sir.",
    "speed": 1.0,
    "audio_description": "polite, indifferent",
    "trailing_silence_s": 0.3,
    "start_s": 138.34671500000005,
    "end_s": 139.62372200000004,
    "duration_s": 1.277007
  },
  {
    "character_identifier": "ROMEO",
    "scene_identifier": "SCENE_01",
    "ordinal": 19,
    "text": "O, she doth teach the torches to burn bright! It seems she hangs upon the cheek of night as a rich jewel in an Ethiop’s ear; beauty too rich for use, for earth too dear! So shows a snowy dove trooping with crows as yonder lady o’er her fellows shows.",
    "speed": 1.0,
    "audio_description": "enraptured, poetic",
    "trailing_silence_s": 0.1,
    "start_s": 139.62372200000004,
    "end_s": 157.07038900000003,
    "duration_s": 17.446667
  },
  {
    "character_identifier": "ROMEO",
    "scene_identifier": "SCENE_01",
    "ordinal": 20,
    "text": "The measure done, I’ll watch her place of stand, and touching hers, make blessed my rude hand. Did my heart love till now? Forswear it, sight! For I ne’er saw true beauty till this night.",
    "speed": 1.0,
    "audio_description": "devoted, awestruck",
    "trailing_silence_s": 0.4,
    "start_s": 157.07038900000003,
    "end_s": 168.89705600000002,
    "duration_s": 11.826667
  },
  {
    "character_identifier": "TYBALT",
    "scene_identifier": "SCENE_01",
    "ordinal": 21,
    "text": "This by his voice, should be a Montague. Fetch me my rapier, boy. What, dares the slave come hither, cover’d with an antic face, to fleer and scorn at our solemnity?",
    "speed": 1.0,
    "audio_description": "vicious, realization",
    "trailing_silence_s": 0.2,
    "start_s": 168.89705600000002,
    "end_s": 179.44372300000003,
    "duration_s": 10.546667
  },
  {
    "character_identifier": "TYBALT",
    "scene_identifier": "SCENE_01",
    "ordinal": 22,
    "text": "Now by the stock and honour of my kin, to strike him dead I hold it not a sin.",
    "speed": 1.0,
    "audio_description": "determined, cold",
    "trailing_silence_s": 0.3,
    "start_s": 179.44372300000003,
    "end_s": 184.53039000000004,
    "duration_s": 5.086667
  },
  {
    "character_identifier": "CAPULET",
    "scene_identifier": "SCENE_01",
    "ordinal": 23,
    "text": "Why how now, kinsman! Wherefore storm you so?",
    "speed": 1.0,
    "audio_description": "noticing, surprised",
    "trailing_silence_s": 0.2,
    "start_s": 184.53039000000004,
    "end_s": 187.67739700000004,
    "duration_s": 3.147007
  },
  {
    "character_identifier": "TYBALT",
    "scene_identifier": "SCENE_01",
    "ordinal": 24,
    "text": "Uncle, this is a Montague, our foe; a villain that is hither come in spite, to scorn at our solemnity this night.",
    "speed": 1.0,
    "audio_description": "furious, accusing",
    "trailing_silence_s": 0.2,
    "start_s": 187.67739700000004,
    "end_s": 194.65440400000006,
    "duration_s": 6.977007
  },
  {
    "character_identifier": "CAPULET",
    "scene_identifier": "SCENE_01",
    "ordinal": 25,
    "text": "Young Romeo, is it?",
    "speed": 1.0,
    "audio_description": "calm, curious",
    "trailing_silence_s": 0.2,
    "start_s": 194.65440400000006,
    "end_s": 196.10141100000007,
    "duration_s": 1.447007
  },
  {
    "character_identifier": "TYBALT",
    "scene_identifier": "SCENE_01",
    "ordinal": 26,
    "text": "’Tis he, that villain Romeo.",
    "speed": 1.0,
    "audio_description": "spitting the words",
    "trailing_silence_s": 0.2,
    "start_s": 196.10141100000007,
    "end_s": 198.74841800000007,
    "duration_s": 2.647007
  },
  {
    "character_identifier": "CAPULET",
    "scene_identifier": "SCENE_01",
    "ordinal": 27,
    "text": "Content thee, gentle coz, let him alone, a bears him like a portly gentleman; and, to say truth, Verona brags of him to be a virtuous and well-govern’d youth. I would not for the wealth of all the town here in my house do him disparagement.",
    "speed": 1.0,
    "audio_description": "measured, firm",
    "trailing_silence_s": 0.1,
    "start_s": 198.74841800000007,
    "end_s": 215.23508500000008,
    "duration_s": 16.486667
  },
  {
    "character_identifier": "CAPULET",
    "scene_identifier": "SCENE_01",
    "ordinal": 28,
    "text": "Therefore be patient, take no note of him, it is my will; the which if thou respect, show a fair presence and put off these frowns, an ill-beseeming semblance for a feast.",
    "speed": 1.0,
    "audio_description": "authoritative",
    "trailing_silence_s": 0.2,
    "start_s": 215.23508500000008,
    "end_s": 225.14209200000008,
    "duration_s": 9.907007
  },
  {
    "character_identifier": "TYBALT",
    "scene_identifier": "SCENE_01",
    "ordinal": 29,
    "text": "It fits when such a villain is a guest: I’ll not endure him.",
    "speed": 1.0,
    "audio_description": "defiant, angry",
    "trailing_silence_s": 0.2,
    "start_s": 225.14209200000008,
    "end_s": 228.96875900000006,
    "duration_s": 3.826667
  },
  {
    "character_identifier": "CAPULET",
    "scene_identifier": "SCENE_01",
    "ordinal": 30,
    "text": "He shall be endur’d. What, goodman boy! I say he shall, go to; am I the master here, or you? Go to. You’ll not endure him! God shall mend my soul, you’ll make a mutiny among my guests!",
    "speed": 1.0,
    "audio_description": "exploding in rage",
    "trailing_silence_s": 0.1,
    "start_s": 228.96875900000006,
    "end_s": 242.09542600000006,
    "duration_s": 13.126667
  },
  {
    "character_identifier": "CAPULET",
    "scene_identifier": "SCENE_01",
    "ordinal": 31,
    "text": "You will set cock-a-hoop, you’ll be the man!",
    "speed": 1.0,
    "audio_description": "scathing",
    "trailing_silence_s": 0.2,
    "start_s": 242.09542600000006,
    "end_s": 244.95243300000007,
    "duration_s": 2.857007
  },
  {
    "character_identifier": "TYBALT",
    "scene_identifier": "SCENE_01",
    "ordinal": 32,
    "text": "Why, uncle, ’tis a shame.",
    "speed": 1.0,
    "audio_description": "muttering",
    "trailing_silence_s": 0.2,
    "start_s": 244.95243300000007,
    "end_s": 246.69910000000007,
    "duration_s": 1.746667
  },
  {
    "character_identifier": "CAPULET",
    "scene_identifier": "SCENE_01",
    "ordinal": 33,
    "text": "Go to, go to! You are a saucy boy. Is’t so, indeed? This trick may chance to scathe you, I know what. You must contrary me! Marry, ’tis time.",
    "speed": 1.0,
    "audio_description": "insulting, threatening",
    "trailing_silence_s": 0.1,
    "start_s": 246.69910000000007,
    "end_s": 257.6657670000001,
    "duration_s": 10.966667
  },
  {
    "character_identifier": "CAPULET",
    "scene_identifier": "SCENE_01",
    "ordinal": 34,
    "text": "Well said, my hearts!—You are a princox; go: be quiet, or—More light, more light!—For shame! I’ll make you quiet. What, cheerly, my hearts.",
    "speed": 1.0,
    "audio_description": "switching between rage and host",
    "trailing_silence_s": 0.4,
    "start_s": 257.6657670000001,
    "end_s": 268.2124340000001,
    "duration_s": 10.546667
  },
  {
    "character_identifier": "TYBALT",
    "scene_identifier": "SCENE_01",
    "ordinal": 35,
    "text": "Patience perforce with wilful choler meeting makes my flesh tremble in their different greeting. I will withdraw: but this intrusion shall, now seeming sweet, convert to bitter gall.",
    "speed": 1.0,
    "audio_description": "trembling with suppressed fury",
    "trailing_silence_s": 0.5,
    "start_s": 268.2124340000001,
    "end_s": 280.3391010000001,
    "duration_s": 12.126667
  },
  {
    "character_identifier": "NARRATOR",
    "scene_identifier": "SCENE_01",
    "ordinal": 36,
    "text": "Tybalt storms away. Amidst the swirling dancers, Romeo finds Juliet and reaches for her hand, his touch light and reverent.",
    "speed": 1.0,
    "audio_description": "narrating",
    "trailing_silence_s": 0.5,
    "start_s": 280.3391010000001,
    "end_s": 288.67910100000006,
    "duration_s": 8.34
  },
  {
    "character_identifier": "ROMEO",
    "scene_identifier": "SCENE_01",
    "ordinal": 37,
    "text": "If I profane with my unworthiest hand this holy shrine, the gentle sin is this, my lips, two blushing pilgrims, ready stand to smooth that rough touch with a tender kiss.",
    "speed": 1.0,
    "audio_description": "gentle, flirtatious",
    "trailing_silence_s": 0.2,
    "start_s": 288.67910100000006,
    "end_s": 299.70576800000003,
    "duration_s": 11.026667
  },
  {
    "character_identifier": "JULIET",
    "scene_identifier": "SCENE_01",
    "ordinal": 38,
    "text": "Good pilgrim, you do wrong your hand too much, which mannerly devotion shows in this; for saints have hands that pilgrims’ hands do touch, and palm to palm is holy palmers’ kiss.",
    "speed": 1.0,
    "audio_description": "witty, playful",
    "trailing_silence_s": 0.2,
    "start_s": 299.70576800000003,
    "end_s": 310.172435,
    "duration_s": 10.466667
  },
  {
    "character_identifier": "ROMEO",
    "scene_identifier": "SCENE_01",
    "ordinal": 39,
    "text": "Have not saints lips, and holy palmers too?",
    "speed": 1.0,
    "audio_description": "softly inquiring",
    "trailing_silence_s": 0.2,
    "start_s": 310.172435,
    "end_s": 313.309442,
    "duration_s": 3.137007
  },
  {
    "character_identifier": "JULIET",
    "scene_identifier": "SCENE_01",
    "ordinal": 40,
    "text": "Ay, pilgrim, lips that they must use in prayer.",
    "speed": 1.0,
    "audio_description": "smiling",
    "trailing_silence_s": 0.2,
    "start_s": 313.309442,
    "end_s": 316.496109,
    "duration_s": 3.186667
  },
  {
    "character_identifier": "ROMEO",
    "scene_identifier": "SCENE_01",
    "ordinal": 41,
    "text": "O, then, dear saint, let lips do what hands do: they pray, grant thou, lest faith turn to despair.",
    "speed": 1.0,
    "audio_description": "earnest",
    "trailing_silence_s": 0.2,
    "start_s": 316.496109,
    "end_s": 323.123116,
    "duration_s": 6.627007
  },
  {
    "character_identifier": "JULIET",
    "scene_identifier": "SCENE_01",
    "ordinal": 42,
    "text": "Saints do not move, though grant for prayers’ sake.",
    "speed": 1.0,
    "audio_description": "teasing",
    "trailing_silence_s": 0.2,
    "start_s": 323.123116,
    "end_s": 326.469783,
    "duration_s": 3.346667
  },
  {
    "character_identifier": "ROMEO",
    "scene_identifier": "SCENE_01",
    "ordinal": 43,
    "text": "Then move not while my prayer’s effect I take. Thus from my lips, by thine my sin is purged.",
    "speed": 1.0,
    "audio_description": "tender",
    "trailing_silence_s": 0.3,
    "start_s": 326.469783,
    "end_s": 333.69264,
    "duration_s": 7.222857
  },
  {
    "character_identifier": "NARRATOR",
    "scene_identifier": "SCENE_01",
    "ordinal": 44,
    "text": "He leans in and they share a brief, soft kiss.",
    "speed": 1.0,
    "audio_description": "narrating",
    "trailing_silence_s": 0.5,
    "start_s": 333.69264,
    "end_s": 336.95264,
    "duration_s": 3.26
  },
  {
    "character_identifier": "JULIET",
    "scene_identifier": "SCENE_01",
    "ordinal": 45,
    "text": "Then have my lips the sin that they have took.",
    "speed": 1.0,
    "audio_description": "whispered, coy",
    "trailing_silence_s": 0.2,
    "start_s": 336.95264,
    "end_s": 339.539828,
    "duration_s": 2.587188
  },
  {
    "character_identifier": "ROMEO",
    "scene_identifier": "SCENE_01",
    "ordinal": 46,
    "text": "Sin from my lips? O trespass sweetly urg! Give me my sin again.",
    "speed": 1.0,
    "audio_description": "smiling",
    "trailing_silence_s": 0.3,
    "start_s": 339.539828,
    "end_s": 344.706495,
    "duration_s": 5.166667
  },
  {
    "character_identifier": "NARRATOR",
    "scene_identifier": "SCENE_01",
    "ordinal": 47,
    "text": "He kisses her a second time.",
    "speed": 1.0,
    "audio_description": "narrating",
    "trailing_silence_s": 0.4,
    "start_s": 344.706495,
    "end_s": 346.86649500000004,
    "duration_s": 2.16
  },
  {
    "character_identifier": "JULIET",
    "scene_identifier": "SCENE_01",
    "ordinal": 48,
    "text": "You kiss by the book.",
    "speed": 1.0,
    "audio_description": "impressed",
    "trailing_silence_s": 0.3,
    "start_s": 346.86649500000004,
    "end_s": 348.393162,
    "duration_s": 1.526667
  },
  {
    "character_identifier": "NURSE",
    "scene_identifier": "SCENE_01",
    "ordinal": 49,
    "text": "Madam, your mother craves a word with you.",
    "speed": 1.0,
    "audio_description": "interrupting, bustling",
    "trailing_silence_s": 0.3,
    "start_s": 348.393162,
    "end_s": 350.99982900000003,
    "duration_s": 2.606667
  },
  {
    "character_identifier": "NARRATOR",
    "scene_identifier": "SCENE_01",
    "ordinal": 50,
    "text": "Juliet pulls away and hurries toward her mother across the room.",
    "speed": 1.0,
    "audio_description": "narrating",
    "trailing_silence_s": 0.3,
    "start_s": 350.99982900000003,
    "end_s": 354.899829,
    "duration_s": 3.9
  },
  {
    "character_identifier": "ROMEO",
    "scene_identifier": "SCENE_01",
    "ordinal": 51,
    "text": "What is her mother?",
    "speed": 1.0,
    "audio_description": "dazed",
    "trailing_silence_s": 0.2,
    "start_s": 354.899829,
    "end_s": 355.846836,
    "duration_s": 0.947007
  },
  {
    "character_identifier": "NURSE",
    "scene_identifier": "SCENE_01",
    "ordinal": 52,
    "text": "Marry, bachelor, her mother is the lady of the house, and a good lady, and a wise and virtuous. I nurs’d her daughter that you talk’d withal. I tell you, he that can lay hold of her shall have the chinks.",
    "speed": 1.0,
    "audio_description": "gossiping, proud",
    "trailing_silence_s": 0.2,
    "start_s": 355.846836,
    "end_s": 367.633843,
    "duration_s": 11.787007
  },
  {
    "character_identifier": "ROMEO",
    "scene_identifier": "SCENE_01",
    "ordinal": 53,
    "text": "Is she a Capulet? O dear account! My life is my foe’s debt.",
    "speed": 1.0,
    "audio_description": "horrified, quiet",
    "trailing_silence_s": 0.4,
    "start_s": 367.633843,
    "end_s": 373.06051,
    "duration_s": 5.426667
  },
  {
    "character_identifier": "BENVOLIO",
    "scene_identifier": "SCENE_01",
    "ordinal": 54,
    "text": "Away, be gone; the sport is at the best.",
    "speed": 1.0,
    "audio_description": "urging, cautious",
    "trailing_silence_s": 0.2,
    "start_s": 373.06051,
    "end_s": 376.025408,
    "duration_s": 2.964898
  },
  {
    "character_identifier": "ROMEO",
    "scene_identifier": "SCENE_01",
    "ordinal": 55,
    "text": "Ay, so I fear; the more is my unrest.",
    "speed": 1.0,
    "audio_description": "troubled",
    "trailing_silence_s": 0.4,
    "start_s": 376.025408,
    "end_s": 379.612075,
    "duration_s": 3.586667
  },
  {
    "character_identifier": "CAPULET",
    "scene_identifier": "SCENE_01",
    "ordinal": 56,
    "text": "Nay, gentlemen, prepare not to be gone, we have a trifling foolish banquet towards. Is it e’en so? Why then, I thank you all; I thank you, honest gentlemen; good night. More torches here! Come on then, let’s to bed. Ah, sirrah, by my fay, it waxes late, I’ll to my rest.",
    "speed": 1.0,
    "audio_description": "weary, hospitable",
    "trailing_silence_s": 0.6,
    "start_s": 379.612075,
    "end_s": 398.21506800000003,
    "duration_s": 18.602993
  },
  {
    "character_identifier": "NARRATOR",
    "scene_identifier": "SCENE_01",
    "ordinal": 57,
    "text": "The crowd begins to disperse, leaving only Juliet and the Nurse in the cooling hall.",
    "speed": 1.0,
    "audio_description": "narrating",
    "trailing_silence_s": 0.5,
    "start_s": 398.21506800000003,
    "end_s": 403.355068,
    "duration_s": 5.14
  },
  {
    "character_identifier": "JULIET",
    "scene_identifier": "SCENE_01",
    "ordinal": 58,
    "text": "Come hither, Nurse. What is yond gentleman?",
    "speed": 1.0,
    "audio_description": "curious, feigning indifference",
    "trailing_silence_s": 0.2,
    "start_s": 403.355068,
    "end_s": 406.381735,
    "duration_s": 3.026667
  },
  {
    "character_identifier": "NURSE",
    "scene_identifier": "SCENE_01",
    "ordinal": 59,
    "text": "The son and heir of old Tiberio.",
    "speed": 1.0,
    "audio_description": "matter-of-fact",
    "trailing_silence_s": 0.2,
    "start_s": 406.381735,
    "end_s": 408.668742,
    "duration_s": 2.287007
  },
  {
    "character_identifier": "JULIET",
    "scene_identifier": "SCENE_01",
    "ordinal": 60,
    "text": "What’s he that now is going out of door?",
    "speed": 1.0,
    "audio_description": "pointing",
    "trailing_silence_s": 0.2,
    "start_s": 408.668742,
    "end_s": 411.055409,
    "duration_s": 2.386667
  },
  {
    "character_identifier": "NURSE",
    "scene_identifier": "SCENE_01",
    "ordinal": 61,
    "text": "Marry, that I think be young Petruchio.",
    "speed": 1.0,
    "audio_description": "uncertain",
    "trailing_silence_s": 0.2,
    "start_s": 411.055409,
    "end_s": 413.882076,
    "duration_s": 2.826667
  },
  {
    "character_identifier": "JULIET",
    "scene_identifier": "SCENE_01",
    "ordinal": 62,
    "text": "What’s he that follows here, that would not dance?",
    "speed": 1.0,
    "audio_description": "intense",
    "trailing_silence_s": 0.2,
    "start_s": 413.882076,
    "end_s": 416.58869699999997,
    "duration_s": 2.706621
  },
  {
    "character_identifier": "NURSE",
    "scene_identifier": "SCENE_01",
    "ordinal": 63,
    "text": "I know not.",
    "speed": 1.0,
    "audio_description": "shrugging",
    "trailing_silence_s": 0.2,
    "start_s": 416.58869699999997,
    "end_s": 417.935364,
    "duration_s": 1.346667
  },
  {
    "character_identifier": "JULIET",
    "scene_identifier": "SCENE_01",
    "ordinal": 64,
    "text": "Go ask his name. If he be married, my grave is like to be my wedding bed.",
    "speed": 1.0,
    "audio_description": "dramatic, heavy",
    "trailing_silence_s": 0.4,
    "start_s": 417.935364,
    "end_s": 422.922031,
    "duration_s": 4.986667
  },
  {
    "character_identifier": "NURSE",
    "scene_identifier": "SCENE_01",
    "ordinal": 65,
    "text": "His name is Romeo, and a Montague, the only son of your great enemy.",
    "speed": 1.0,
    "audio_description": "grave",
    "trailing_silence_s": 0.3,
    "start_s": 422.922031,
    "end_s": 427.669038,
    "duration_s": 4.747007
  },
  {
    "character_identifier": "JULIET",
    "scene_identifier": "SCENE_01",
    "ordinal": 66,
    "text": "My only love sprung from my only hate! Too early seen unknown, and known too late! Prodigious birth of love it is to me, that I must love a loathed enemy.",
    "speed": 1.0,
    "audio_description": "anguished, realization",
    "trailing_silence_s": 0.4,
    "start_s": 427.669038,
    "end_s": 438.215705,
    "duration_s": 10.546667
  },
  {
    "character_identifier": "NURSE",
    "scene_identifier": "SCENE_01",
    "ordinal": 67,
    "text": "What’s this? What’s this?",
    "speed": 1.0,
    "audio_description": "confused",
    "trailing_silence_s": 0.2,
    "start_s": 438.215705,
    "end_s": 440.222712,
    "duration_s": 2.007007
  },
  {
    "character_identifier": "JULIET",
    "scene_identifier": "SCENE_01",
    "ordinal": 68,
    "text": "A rhyme I learn’d even now of one I danc’d withal.",
    "speed": 1.0,
    "audio_description": "covering up",
    "trailing_silence_s": 0.2,
    "start_s": 440.222712,
    "end_s": 443.489379,
    "duration_s": 3.266667
  },
  {
    "character_identifier": "NARRATOR",
    "scene_identifier": "SCENE_01",
    "ordinal": 69,
    "text": "A voice calls out from the inner rooms: 'Juliet!'",
    "speed": 1.0,
    "audio_description": "atmospheric",
    "trailing_silence_s": 0.2,
    "start_s": 443.489379,
    "end_s": 446.44937899999996,
    "duration_s": 2.96
  },
  {
    "character_identifier": "NURSE",
    "scene_identifier": "SCENE_01",
    "ordinal": 70,
    "text": "Anon, anon! Come let’s away, the strangers all are gone.",
    "speed": 1.0,
    "audio_description": "hurrying",
    "trailing_silence_s": 0.5,
    "start_s": 446.44937899999996,
    "end_s": 450.496046,
    "duration_s": 4.046667
  }
]